test_matrix.py
src/testmatrix/__init__.py
src/testmatrix/jwtauth.py
src/testmatrix/matrixserver.py
src/testmatrix/utils.py
testmatrix-0.2.0.dist-info/licenses/LICENSE
testmatrix-0.2.0.dist-info/METADATA
testmatrix-0.2.0.dist-info/WHEEL
testmatrix-0.2.0.dist-info/entry_points.txt
testmatrix-0.2.0.dist-info/top_level.txt
testmatrix-0.2.0.dist-info/RECORD
