Metadata-Version: 2.4
Name: testmatrix
Version: 0.2.0
Summary: A matrix server sanity tester
Author-email: Sebastian Spaeth <Sebastian@SSpaeth.de>
License-Expression: AGPL-3.0-or-later
Project-URL: source, https://codeberg.org/spaetz/testmatrix
Project-URL: issues, https://codeberg.org/spaetz/testmatrix/issues
Project-URL: chatroom, https://matrix.to/#/%23testmatrix:sspaeth.de
Keywords: matrix,chat,collaboration
Classifier: Programming Language :: Python :: 3
Classifier: Operating System :: OS Independent
Classifier: Intended Audience :: Developers
Requires-Python: >=3.10
License-File: LICENSE
Requires-Dist: requests
Dynamic: license-file
